pale_signal/__init__.py
pale_signal/analytics.py
pale_signal/cli.py
pale_signal/data_store.py
pale_signal/dummy_data.py
pale_signal/visualize.py
pale_signal-1.0.4.dist-info/licenses/LICENSE
pale_signal-1.0.4.dist-info/METADATA
pale_signal-1.0.4.dist-info/WHEEL
pale_signal-1.0.4.dist-info/entry_points.txt
pale_signal-1.0.4.dist-info/top_level.txt
pale_signal-1.0.4.dist-info/RECORD
