Metadata-Version: 2.4
Name: pale-signal
Version: 1.0.4
Summary: A lightweight, local-first CLI tool for tracking and analyzing daily life signals
License: MIT
Requires-Python: >=3.8
License-File: LICENSE
Requires-Dist: matplotlib>=3.8.0
Dynamic: license-file
